[{"nomAula":"A6101","dies":[{"0":[{"hora":9,"numGrup":12,"nomAssig":"AC","tipus":"PROBLEMES"}]},{"1":[]},{"2":[]},{"3":[]},{"4":[]}]},{"nomAula":"A5206","dies":[{"0":[]},{"1":[{"hora":8,"numGrup":12,"nomAssig":"AC","tipus":"PROBLEMES"}]},{"2":[]},{"3":[]},{"4":[]}]},{"nomAula":"C6S03","dies":[{"0":[]},{"1":[]},{"2":[]},{"3":[]},{"4":[{"hora":17,"numGrup":21,"nomAssig":"F","tipus":"LABORATORI"}]}]},{"nomAula":"C6S05","dies":[{"0":[]},{"1":[]},{"2":[{"hora":15,"numGrup":21,"nomAssig":"F","tipus":"LABORATORI"}]},{"3":[]},{"4":[]}]},{"nomAula":"A5202","dies":[{"0":[{"hora":8,"numGrup":12,"nomAssig":"AC","tipus":"PROBLEMES"}]},{"1":[]},{"2":[]},{"3":[]},{"4":[]}]},{"nomAula":"A5S02","dies":[{"0":[]},{"1":[{"hora":19,"numGrup":21,"nomAssig":"F","tipus":"LABORATORI"}]},{"2":[]},{"3":[]},{"4":[]}]},{"nomAula":"A5203","dies":[{"0":[{"hora":11,"numGrup":12,"nomAssig":"AC","tipus":"PROBLEMES"}]},{"1":[]},{"2":[]},{"3":[]},{"4":[]}]},{"nomAula":"C6S04","dies":[{"0":[]},{"1":[]},{"2":[]},{"3":[{"hora":15,"numGrup":21,"nomAssig":"F","tipus":"LABORATORI"}]},{"4":[]}]},{"nomAula":"C6S07","dies":[{"0":[{"hora":16,"numGrup":21,"nomAssig":"F","tipus":"LABORATORI"}]},{"1":[]},{"2":[]},{"3":[]},{"4":[]}]},{"nomAula":"A5204","dies":[{"0":[]},{"1":[]},{"2":[]},{"3":[{"hora":17,"numGrup":23,"nomAssig":"F","tipus":"PROBLEMES"}]},{"4":[]}]},{"nomAula":"A5205","dies":[{"0":[]},{"1":[]},{"2":[{"hora":12,"numGrup":12,"nomAssig":"AC","tipus":"PROBLEMES"}]},{"3":[]},{"4":[]}]},{"nomAula":"C6S06","dies":[{"0":[]},{"1":[{"hora":14,"numGrup":21,"nomAssig":"F","tipus":"LABORATORI"}]},{"2":[]},{"3":[]},{"4":[]}]}]